[
  {
    "id": 7,
    "documentId": "mrhxlq06o7hz31wv0j9tbmw7",
    "Title": "Vero Selaras: Villa Ubud Made Heng",
    "createdAt": "2025-04-14T18:50:24.201Z",
    "updatedAt": "2025-04-14T20:53:46.081Z",
    "publishedAt": "2025-04-14T20:53:46.094Z",
    "Description": null,
    "IsFeatured": true,
    "Price": 440000000,
    "Bedrooms": 2,
    "Bathrooms": 3,
    "Area": 100,
    "PropertyType": "Villa",
    "Slug": "vero-selaras-villa-ubud-made-heng",
    "Location": "Ubud, Bali",
    "YearBuilt": 2024,
    "Furnishing": "Fully Furnished",
    "Availability": "Available Now",
    "Status": "For Rent",
    "LandSize": 0,
    "Image": [
      {
        "id": 6,
        "documentId": "l9w8z3bswuj00h9ebuckt9uq",
        "name": "Bathroom-1-1.jpg",
        "alternativeText": null,
        "caption": null,
        "width": 1600,
        "height": 900,
        "formats": {
          "thumbnail": {
            "name": "thumbnail_Bathroom-1-1.jpg",
            "hash": "thumbnail_Bathroom_1_1_dee52c2a66",
            "ext": ".jpg",
            "mime": "image/jpeg",
            "path": null,
            "width": 245,
            "height": 138,
            "size": 6.41,
            "sizeInBytes": 6412,
            "url": "/uploads/thumbnail_Bathroom_1_1_dee52c2a66.jpg"
          },
          "large": {
            "name": "large_Bathroom-1-1.jpg",
            "hash": "large_Bathroom_1_1_dee52c2a66",
            "ext": ".jpg",
            "mime": "image/jpeg",
            "path": null,
            "width": 1000,
            "height": 563,
            "size": 60.86,
            "sizeInBytes": 60859,
            "url": "/uploads/large_Bathroom_1_1_dee52c2a66.jpg"
          },
          "small": {
            "name": "small_Bathroom-1-1.jpg",
            "hash": "small_Bathroom_1_1_dee52c2a66",
            "ext": ".jpg",
            "mime": "image/jpeg",
            "path": null,
            "width": 500,
            "height": 281,
            "size": 19.57,
            "sizeInBytes": 19568,
            "url": "/uploads/small_Bathroom_1_1_dee52c2a66.jpg"
          },
          "medium": {
            "name": "medium_Bathroom-1-1.jpg",
            "hash": "medium_Bathroom_1_1_dee52c2a66",
            "ext": ".jpg",
            "mime": "image/jpeg",
            "path": null,
            "width": 750,
            "height": 422,
            "size": 37.87,
            "sizeInBytes": 37868,
            "url": "/uploads/medium_Bathroom_1_1_dee52c2a66.jpg"
          }
        },
        "hash": "Bathroom_1_1_dee52c2a66",
        "ext": ".jpg",
        "mime": "image/jpeg",
        "size": 107.17,
        "url": "/uploads/Bathroom_1_1_dee52c2a66.jpg",
        "previewUrl": null,
        "provider": "local",
        "provider_metadata": null,
        "createdAt": "2025-04-14T18:47:17.088Z",
        "updatedAt": "2025-04-14T18:47:17.088Z",
        "publishedAt": "2025-04-14T18:47:17.089Z"
      },
      {
        "id": 8,
        "documentId": "nkuf5xgckfpitw537aiifsa6",
        "name": "Bathroom-2-1.jpg",
        "alternativeText": null,
        "caption": null,
        "width": 900,
        "height": 1600,
        "formats": {
          "thumbnail": {
            "name": "thumbnail_Bathroom-2-1.jpg",
            "hash": "thumbnail_Bathroom_2_1_3a2b08cc34",
            "ext": ".jpg",
            "mime": "image/jpeg",
            "path": null,
            "width": 87,
            "height": 156,
            "size": 2.64,
            "sizeInBytes": 2640,
            "url": "/uploads/thumbnail_Bathroom_2_1_3a2b08cc34.jpg"
          },
          "medium": {
            "name": "medium_Bathroom-2-1.jpg",
            "hash": "medium_Bathroom_2_1_3a2b08cc34",
            "ext": ".jpg",
            "mime": "image/jpeg",
            "path": null,
            "width": 422,
            "height": 750,
            "size": 43.79,
            "sizeInBytes": 43789,
            "url": "/uploads/medium_Bathroom_2_1_3a2b08cc34.jpg"
          },
          "small": {
            "name": "small_Bathroom-2-1.jpg",
            "hash": "small_Bathroom_2_1_3a2b08cc34",
            "ext": ".jpg",
            "mime": "image/jpeg",
            "path": null,
            "width": 281,
            "height": 500,
            "size": 19.91,
            "sizeInBytes": 19914,
            "url": "/uploads/small_Bathroom_2_1_3a2b08cc34.jpg"
          },
          "large": {
            "name": "large_Bathroom-2-1.jpg",
            "hash": "large_Bathroom_2_1_3a2b08cc34",
            "ext": ".jpg",
            "mime": "image/jpeg",
            "path": null,
            "width": 563,
            "height": 1000,
            "size": 75.77,
            "sizeInBytes": 75766,
            "url": "/uploads/large_Bathroom_2_1_3a2b08cc34.jpg"
          }
        },
        "hash": "Bathroom_2_1_3a2b08cc34",
        "ext": ".jpg",
        "mime": "image/jpeg",
        "size": 154.71,
        "url": "/uploads/Bathroom_2_1_3a2b08cc34.jpg",
        "previewUrl": null,
        "provider": "local",
        "provider_metadata": null,
        "createdAt": "2025-04-14T18:47:17.132Z",
        "updatedAt": "2025-04-14T18:47:17.132Z",
        "publishedAt": "2025-04-14T18:47:17.132Z"
      },
      {
        "id": 7,
        "documentId": "b23v7i2jul2wady1tk0gkl2j",
        "name": "Bathroom-2-2.jpg",
        "alternativeText": null,
        "caption": null,
        "width": 1600,
        "height": 900,
        "formats": {
          "thumbnail": {
            "name": "thumbnail_Bathroom-2-2.jpg",
            "hash": "thumbnail_Bathroom_2_2_3a17496b27",
            "ext": ".jpg",
            "mime": "image/jpeg",
            "path": null,
            "width": 245,
            "height": 138,
            "size": 7.37,
            "sizeInBytes": 7370,
            "url": "/uploads/thumbnail_Bathroom_2_2_3a17496b27.jpg"
          },
          "medium": {
            "name": "medium_Bathroom-2-2.jpg",
            "hash": "medium_Bathroom_2_2_3a17496b27",
            "ext": ".jpg",
            "mime": "image/jpeg",
            "path": null,
            "width": 750,
            "height": 422,
            "size": 50.91,
            "sizeInBytes": 50909,
            "url": "/uploads/medium_Bathroom_2_2_3a17496b27.jpg"
          },
          "small": {
            "name": "small_Bathroom-2-2.jpg",
            "hash": "small_Bathroom_2_2_3a17496b27",
            "ext": ".jpg",
            "mime": "image/jpeg",
            "path": null,
            "width": 500,
            "height": 281,
            "size": 24.7,
            "sizeInBytes": 24699,
            "url": "/uploads/small_Bathroom_2_2_3a17496b27.jpg"
          },
          "large": {
            "name": "large_Bathroom-2-2.jpg",
            "hash": "large_Bathroom_2_2_3a17496b27",
            "ext": ".jpg",
            "mime": "image/jpeg",
            "path": null,
            "width": 1000,
            "height": 563,
            "size": 84.38,
            "sizeInBytes": 84375,
            "url": "/uploads/large_Bathroom_2_2_3a17496b27.jpg"
          }
        },
        "hash": "Bathroom_2_2_3a17496b27",
        "ext": ".jpg",
        "mime": "image/jpeg",
        "size": 160.87,
        "url": "/uploads/Bathroom_2_2_3a17496b27.jpg",
        "previewUrl": null,
        "provider": "local",
        "provider_metadata": null,
        "createdAt": "2025-04-14T18:47:17.129Z",
        "updatedAt": "2025-04-14T18:47:17.129Z",
        "publishedAt": "2025-04-14T18:47:17.129Z"
      },
      {
        "id": 9,
        "documentId": "ml0r7gp8gdpzyyjtpituo3q5",
        "name": "Bathroom-3-1.jpg",
        "alternativeText": null,
        "caption": null,
        "width": 900,
        "height": 1600,
        "formats": {
          "thumbnail": {
            "name": "thumbnail_Bathroom-3-1.jpg",
            "hash": "thumbnail_Bathroom_3_1_173ba1ee53",
            "ext": ".jpg",
            "mime": "image/jpeg",
            "path": null,
            "width": 87,
            "height": 156,
            "size": 2.89,
            "sizeInBytes": 2886,
            "url": "/uploads/thumbnail_Bathroom_3_1_173ba1ee53.jpg"
          },
          "medium": {
            "name": "medium_Bathroom-3-1.jpg",
            "hash": "medium_Bathroom_3_1_173ba1ee53",
            "ext": ".jpg",
            "mime": "image/jpeg",
            "path": null,
            "width": 422,
            "height": 750,
            "size": 39.84,
            "sizeInBytes": 39835,
            "url": "/uploads/medium_Bathroom_3_1_173ba1ee53.jpg"
          },
          "small": {
            "name": "small_Bathroom-3-1.jpg",
            "hash": "small_Bathroom_3_1_173ba1ee53",
            "ext": ".jpg",
            "mime": "image/jpeg",
            "path": null,
            "width": 281,
            "height": 500,
            "size": 19.47,
            "sizeInBytes": 19465,
            "url": "/uploads/small_Bathroom_3_1_173ba1ee53.jpg"
          },
          "large": {
            "name": "large_Bathroom-3-1.jpg",
            "hash": "large_Bathroom_3_1_173ba1ee53",
            "ext": ".jpg",
            "mime": "image/jpeg",
            "path": null,
            "width": 563,
            "height": 1000,
            "size": 65.66,
            "sizeInBytes": 65659,
            "url": "/uploads/large_Bathroom_3_1_173ba1ee53.jpg"
          }
        },
        "hash": "Bathroom_3_1_173ba1ee53",
        "ext": ".jpg",
        "mime": "image/jpeg",
        "size": 120.75,
        "url": "/uploads/Bathroom_3_1_173ba1ee53.jpg",
        "previewUrl": null,
        "provider": "local",
        "provider_metadata": null,
        "createdAt": "2025-04-14T18:47:17.134Z",
        "updatedAt": "2025-04-14T18:47:17.134Z",
        "publishedAt": "2025-04-14T18:47:17.135Z"
      },
      {
        "id": 10,
        "documentId": "fz6tv3um1keeayj4ad7n8h2c",
        "name": "Balcony-1.jpg",
        "alternativeText": null,
        "caption": null,
        "width": 1600,
        "height": 900,
        "formats": {
          "thumbnail": {
            "name": "thumbnail_Balcony-1.jpg",
            "hash": "thumbnail_Balcony_1_1f2180a5d8",
            "ext": ".jpg",
            "mime": "image/jpeg",
            "path": null,
            "width": 245,
            "height": 138,
            "size": 13.39,
            "sizeInBytes": 13394,
            "url": "/uploads/thumbnail_Balcony_1_1f2180a5d8.jpg"
          },
          "small": {
            "name": "small_Balcony-1.jpg",
            "hash": "small_Balcony_1_1f2180a5d8",
            "ext": ".jpg",
            "mime": "image/jpeg",
            "path": null,
            "width": 500,
            "height": 281,
            "size": 48.21,
            "sizeInBytes": 48214,
            "url": "/uploads/small_Balcony_1_1f2180a5d8.jpg"
          },
          "medium": {
            "name": "medium_Balcony-1.jpg",
            "hash": "medium_Balcony_1_1f2180a5d8",
            "ext": ".jpg",
            "mime": "image/jpeg",
            "path": null,
            "width": 750,
            "height": 422,
            "size": 100.91,
            "sizeInBytes": 100905,
            "url": "/uploads/medium_Balcony_1_1f2180a5d8.jpg"
          },
          "large": {
            "name": "large_Balcony-1.jpg",
            "hash": "large_Balcony_1_1f2180a5d8",
            "ext": ".jpg",
            "mime": "image/jpeg",
            "path": null,
            "width": 1000,
            "height": 563,
            "size": 165.08,
            "sizeInBytes": 165082,
            "url": "/uploads/large_Balcony_1_1f2180a5d8.jpg"
          }
        },
        "hash": "Balcony_1_1f2180a5d8",
        "ext": ".jpg",
        "mime": "image/jpeg",
        "size": 313.95,
        "url": "/uploads/Balcony_1_1f2180a5d8.jpg",
        "previewUrl": null,
        "provider": "local",
        "provider_metadata": null,
        "createdAt": "2025-04-14T18:47:17.140Z",
        "updatedAt": "2025-04-14T18:47:17.140Z",
        "publishedAt": "2025-04-14T18:47:17.140Z"
      },
      {
        "id": 11,
        "documentId": "wfdvzl8nb4u4s56qjzvl4zhf",
        "name": "Bedroom-1-1.jpg",
        "alternativeText": null,
        "caption": null,
        "width": 1600,
        "height": 900,
        "formats": {
          "thumbnail": {
            "name": "thumbnail_Bedroom-1-1.jpg",
            "hash": "thumbnail_Bedroom_1_1_2bf8d55856",
            "ext": ".jpg",
            "mime": "image/jpeg",
            "path": null,
            "width": 245,
            "height": 138,
            "size": 7.18,
            "sizeInBytes": 7182,
            "url": "/uploads/thumbnail_Bedroom_1_1_2bf8d55856.jpg"
          },
          "large": {
            "name": "large_Bedroom-1-1.jpg",
            "hash": "large_Bedroom_1_1_2bf8d55856",
            "ext": ".jpg",
            "mime": "image/jpeg",
            "path": null,
            "width": 1000,
            "height": 563,
            "size": 64.89,
            "sizeInBytes": 64893,
            "url": "/uploads/large_Bedroom_1_1_2bf8d55856.jpg"
          },
          "small": {
            "name": "small_Bedroom-1-1.jpg",
            "hash": "small_Bedroom_1_1_2bf8d55856",
            "ext": ".jpg",
            "mime": "image/jpeg",
            "path": null,
            "width": 500,
            "height": 281,
            "size": 21.41,
            "sizeInBytes": 21411,
            "url": "/uploads/small_Bedroom_1_1_2bf8d55856.jpg"
          },
          "medium": {
            "name": "medium_Bedroom-1-1.jpg",
            "hash": "medium_Bedroom_1_1_2bf8d55856",
            "ext": ".jpg",
            "mime": "image/jpeg",
            "path": null,
            "width": 750,
            "height": 422,
            "size": 40.64,
            "sizeInBytes": 40644,
            "url": "/uploads/medium_Bedroom_1_1_2bf8d55856.jpg"
          }
        },
        "hash": "Bedroom_1_1_2bf8d55856",
        "ext": ".jpg",
        "mime": "image/jpeg",
        "size": 115.37,
        "url": "/uploads/Bedroom_1_1_2bf8d55856.jpg",
        "previewUrl": null,
        "provider": "local",
        "provider_metadata": null,
        "createdAt": "2025-04-14T18:47:17.145Z",
        "updatedAt": "2025-04-14T18:47:17.145Z",
        "publishedAt": "2025-04-14T18:47:17.145Z"
      },
      {
        "id": 12,
        "documentId": "r9ju2p0za9dy3ci4ume76xz0",
        "name": "Bedroom-1-2.jpg",
        "alternativeText": null,
        "caption": null,
        "width": 1600,
        "height": 900,
        "formats": {
          "thumbnail": {
            "name": "thumbnail_Bedroom-1-2.jpg",
            "hash": "thumbnail_Bedroom_1_2_47b7069ea3",
            "ext": ".jpg",
            "mime": "image/jpeg",
            "path": null,
            "width": 245,
            "height": 138,
            "size": 6.74,
            "sizeInBytes": 6744,
            "url": "/uploads/thumbnail_Bedroom_1_2_47b7069ea3.jpg"
          },
          "large": {
            "name": "large_Bedroom-1-2.jpg",
            "hash": "large_Bedroom_1_2_47b7069ea3",
            "ext": ".jpg",
            "mime": "image/jpeg",
            "path": null,
            "width": 1000,
            "height": 563,
            "size": 60.59,
            "sizeInBytes": 60586,
            "url": "/uploads/large_Bedroom_1_2_47b7069ea3.jpg"
          },
          "medium": {
            "name": "medium_Bedroom-1-2.jpg",
            "hash": "medium_Bedroom_1_2_47b7069ea3",
            "ext": ".jpg",
            "mime": "image/jpeg",
            "path": null,
            "width": 750,
            "height": 422,
            "size": 38.06,
            "sizeInBytes": 38058,
            "url": "/uploads/medium_Bedroom_1_2_47b7069ea3.jpg"
          },
          "small": {
            "name": "small_Bedroom-1-2.jpg",
            "hash": "small_Bedroom_1_2_47b7069ea3",
            "ext": ".jpg",
            "mime": "image/jpeg",
            "path": null,
            "width": 500,
            "height": 281,
            "size": 19.97,
            "sizeInBytes": 19973,
            "url": "/uploads/small_Bedroom_1_2_47b7069ea3.jpg"
          }
        },
        "hash": "Bedroom_1_2_47b7069ea3",
        "ext": ".jpg",
        "mime": "image/jpeg",
        "size": 105.69,
        "url": "/uploads/Bedroom_1_2_47b7069ea3.jpg",
        "previewUrl": null,
        "provider": "local",
        "provider_metadata": null,
        "createdAt": "2025-04-14T18:47:17.437Z",
        "updatedAt": "2025-04-14T18:47:17.437Z",
        "publishedAt": "2025-04-14T18:47:17.437Z"
      },
      {
        "id": 13,
        "documentId": "gq3wamy3tt1nn40nt57ihgq0",
        "name": "Bedroom-2-1.jpg",
        "alternativeText": null,
        "caption": null,
        "width": 1600,
        "height": 900,
        "formats": {
          "thumbnail": {
            "name": "thumbnail_Bedroom-2-1.jpg",
            "hash": "thumbnail_Bedroom_2_1_bd62ea63dd",
            "ext": ".jpg",
            "mime": "image/jpeg",
            "path": null,
            "width": 245,
            "height": 138,
            "size": 6.81,
            "sizeInBytes": 6813,
            "url": "/uploads/thumbnail_Bedroom_2_1_bd62ea63dd.jpg"
          },
          "medium": {
            "name": "medium_Bedroom-2-1.jpg",
            "hash": "medium_Bedroom_2_1_bd62ea63dd",
            "ext": ".jpg",
            "mime": "image/jpeg",
            "path": null,
            "width": 750,
            "height": 422,
            "size": 41.72,
            "sizeInBytes": 41723,
            "url": "/uploads/medium_Bedroom_2_1_bd62ea63dd.jpg"
          },
          "small": {
            "name": "small_Bedroom-2-1.jpg",
            "hash": "small_Bedroom_2_1_bd62ea63dd",
            "ext": ".jpg",
            "mime": "image/jpeg",
            "path": null,
            "width": 500,
            "height": 281,
            "size": 21.33,
            "sizeInBytes": 21325,
            "url": "/uploads/small_Bedroom_2_1_bd62ea63dd.jpg"
          },
          "large": {
            "name": "large_Bedroom-2-1.jpg",
            "hash": "large_Bedroom_2_1_bd62ea63dd",
            "ext": ".jpg",
            "mime": "image/jpeg",
            "path": null,
            "width": 1000,
            "height": 563,
            "size": 66.41,
            "sizeInBytes": 66410,
            "url": "/uploads/large_Bedroom_2_1_bd62ea63dd.jpg"
          }
        },
        "hash": "Bedroom_2_1_bd62ea63dd",
        "ext": ".jpg",
        "mime": "image/jpeg",
        "size": 118.45,
        "url": "/uploads/Bedroom_2_1_bd62ea63dd.jpg",
        "previewUrl": null,
        "provider": "local",
        "provider_metadata": null,
        "createdAt": "2025-04-14T18:47:17.480Z",
        "updatedAt": "2025-04-14T18:47:17.480Z",
        "publishedAt": "2025-04-14T18:47:17.480Z"
      },
      {
        "id": 14,
        "documentId": "xjeuuo072kwwo2czppdj0qwp",
        "name": "Exterior-1.jpg",
        "alternativeText": null,
        "caption": null,
        "width": 900,
        "height": 1600,
        "formats": {
          "thumbnail": {
            "name": "thumbnail_Exterior-1.jpg",
            "hash": "thumbnail_Exterior_1_5968f3b2b7",
            "ext": ".jpg",
            "mime": "image/jpeg",
            "path": null,
            "width": 87,
            "height": 156,
            "size": 4.47,
            "sizeInBytes": 4467,
            "url": "/uploads/thumbnail_Exterior_1_5968f3b2b7.jpg"
          },
          "small": {
            "name": "small_Exterior-1.jpg",
            "hash": "small_Exterior_1_5968f3b2b7",
            "ext": ".jpg",
            "mime": "image/jpeg",
            "path": null,
            "width": 281,
            "height": 500,
            "size": 34.24,
            "sizeInBytes": 34241,
            "url": "/uploads/small_Exterior_1_5968f3b2b7.jpg"
          },
          "large": {
            "name": "large_Exterior-1.jpg",
            "hash": "large_Exterior_1_5968f3b2b7",
            "ext": ".jpg",
            "mime": "image/jpeg",
            "path": null,
            "width": 563,
            "height": 1000,
            "size": 114.93,
            "sizeInBytes": 114928,
            "url": "/uploads/large_Exterior_1_5968f3b2b7.jpg"
          },
          "medium": {
            "name": "medium_Exterior-1.jpg",
            "hash": "medium_Exterior_1_5968f3b2b7",
            "ext": ".jpg",
            "mime": "image/jpeg",
            "path": null,
            "width": 422,
            "height": 750,
            "size": 70.18,
            "sizeInBytes": 70183,
            "url": "/uploads/medium_Exterior_1_5968f3b2b7.jpg"
          }
        },
        "hash": "Exterior_1_5968f3b2b7",
        "ext": ".jpg",
        "mime": "image/jpeg",
        "size": 221.94,
        "url": "/uploads/Exterior_1_5968f3b2b7.jpg",
        "previewUrl": null,
        "provider": "local",
        "provider_metadata": null,
        "createdAt": "2025-04-14T18:47:17.482Z",
        "updatedAt": "2025-04-14T20:18:36.870Z",
        "publishedAt": "2025-04-14T18:47:17.482Z"
      },
      {
        "id": 15,
        "documentId": "tpc93yt4rokpbpq8p0en3lv8",
        "name": "Exterior-2.jpg",
        "alternativeText": null,
        "caption": null,
        "width": 900,
        "height": 1600,
        "formats": {
          "thumbnail": {
            "name": "thumbnail_Exterior-2.jpg",
            "hash": "thumbnail_Exterior_2_c387bebd31",
            "ext": ".jpg",
            "mime": "image/jpeg",
            "path": null,
            "width": 87,
            "height": 156,
            "size": 4.22,
            "sizeInBytes": 4218,
            "url": "/uploads/thumbnail_Exterior_2_c387bebd31.jpg"
          },
          "small": {
            "name": "small_Exterior-2.jpg",
            "hash": "small_Exterior_2_c387bebd31",
            "ext": ".jpg",
            "mime": "image/jpeg",
            "path": null,
            "width": 281,
            "height": 500,
            "size": 31.45,
            "sizeInBytes": 31446,
            "url": "/uploads/small_Exterior_2_c387bebd31.jpg"
          },
          "large": {
            "name": "large_Exterior-2.jpg",
            "hash": "large_Exterior_2_c387bebd31",
            "ext": ".jpg",
            "mime": "image/jpeg",
            "path": null,
            "width": 563,
            "height": 1000,
            "size": 109.14,
            "sizeInBytes": 109138,
            "url": "/uploads/large_Exterior_2_c387bebd31.jpg"
          },
          "medium": {
            "name": "medium_Exterior-2.jpg",
            "hash": "medium_Exterior_2_c387bebd31",
            "ext": ".jpg",
            "mime": "image/jpeg",
            "path": null,
            "width": 422,
            "height": 750,
            "size": 65.77,
            "sizeInBytes": 65766,
            "url": "/uploads/medium_Exterior_2_c387bebd31.jpg"
          }
        },
        "hash": "Exterior_2_c387bebd31",
        "ext": ".jpg",
        "mime": "image/jpeg",
        "size": 214.73,
        "url": "/uploads/Exterior_2_c387bebd31.jpg",
        "previewUrl": null,
        "provider": "local",
        "provider_metadata": null,
        "createdAt": "2025-04-14T18:47:17.484Z",
        "updatedAt": "2025-04-14T18:47:17.484Z",
        "publishedAt": "2025-04-14T18:47:17.484Z"
      },
      {
        "id": 16,
        "documentId": "gnheabmod6j0iacxp30m4tkt",
        "name": "Exterior-5.jpg",
        "alternativeText": null,
        "caption": null,
        "width": 1600,
        "height": 900,
        "formats": {
          "thumbnail": {
            "name": "thumbnail_Exterior-5.jpg",
            "hash": "thumbnail_Exterior_5_19e7a33323",
            "ext": ".jpg",
            "mime": "image/jpeg",
            "path": null,
            "width": 245,
            "height": 138,
            "size": 11.2,
            "sizeInBytes": 11197,
            "url": "/uploads/thumbnail_Exterior_5_19e7a33323.jpg"
          },
          "small": {
            "name": "small_Exterior-5.jpg",
            "hash": "small_Exterior_5_19e7a33323",
            "ext": ".jpg",
            "mime": "image/jpeg",
            "path": null,
            "width": 500,
            "height": 281,
            "size": 38.48,
            "sizeInBytes": 38481,
            "url": "/uploads/small_Exterior_5_19e7a33323.jpg"
          },
          "medium": {
            "name": "medium_Exterior-5.jpg",
            "hash": "medium_Exterior_5_19e7a33323",
            "ext": ".jpg",
            "mime": "image/jpeg",
            "path": null,
            "width": 750,
            "height": 422,
            "size": 80.11,
            "sizeInBytes": 80105,
            "url": "/uploads/medium_Exterior_5_19e7a33323.jpg"
          },
          "large": {
            "name": "large_Exterior-5.jpg",
            "hash": "large_Exterior_5_19e7a33323",
            "ext": ".jpg",
            "mime": "image/jpeg",
            "path": null,
            "width": 1000,
            "height": 563,
            "size": 131.22,
            "sizeInBytes": 131223,
            "url": "/uploads/large_Exterior_5_19e7a33323.jpg"
          }
        },
        "hash": "Exterior_5_19e7a33323",
        "ext": ".jpg",
        "mime": "image/jpeg",
        "size": 250.57,
        "url": "/uploads/Exterior_5_19e7a33323.jpg",
        "previewUrl": null,
        "provider": "local",
        "provider_metadata": null,
        "createdAt": "2025-04-14T18:47:17.487Z",
        "updatedAt": "2025-04-14T18:47:17.487Z",
        "publishedAt": "2025-04-14T18:47:17.487Z"
      },
      {
        "id": 17,
        "documentId": "rgccsrteis32l57xcfd88sp9",
        "name": "Exterior-4.jpg",
        "alternativeText": null,
        "caption": null,
        "width": 900,
        "height": 1600,
        "formats": {
          "thumbnail": {
            "name": "thumbnail_Exterior-4.jpg",
            "hash": "thumbnail_Exterior_4_aa7969549d",
            "ext": ".jpg",
            "mime": "image/jpeg",
            "path": null,
            "width": 87,
            "height": 156,
            "size": 4.6,
            "sizeInBytes": 4595,
            "url": "/uploads/thumbnail_Exterior_4_aa7969549d.jpg"
          },
          "small": {
            "name": "small_Exterior-4.jpg",
            "hash": "small_Exterior_4_aa7969549d",
            "ext": ".jpg",
            "mime": "image/jpeg",
            "path": null,
            "width": 281,
            "height": 500,
            "size": 33.79,
            "sizeInBytes": 33788,
            "url": "/uploads/small_Exterior_4_aa7969549d.jpg"
          },
          "large": {
            "name": "large_Exterior-4.jpg",
            "hash": "large_Exterior_4_aa7969549d",
            "ext": ".jpg",
            "mime": "image/jpeg",
            "path": null,
            "width": 563,
            "height": 1000,
            "size": 112.51,
            "sizeInBytes": 112514,
            "url": "/uploads/large_Exterior_4_aa7969549d.jpg"
          },
          "medium": {
            "name": "medium_Exterior-4.jpg",
            "hash": "medium_Exterior_4_aa7969549d",
            "ext": ".jpg",
            "mime": "image/jpeg",
            "path": null,
            "width": 422,
            "height": 750,
            "size": 68.88,
            "sizeInBytes": 68876,
            "url": "/uploads/medium_Exterior_4_aa7969549d.jpg"
          }
        },
        "hash": "Exterior_4_aa7969549d",
        "ext": ".jpg",
        "mime": "image/jpeg",
        "size": 210.62,
        "url": "/uploads/Exterior_4_aa7969549d.jpg",
        "previewUrl": null,
        "provider": "local",
        "provider_metadata": null,
        "createdAt": "2025-04-14T18:47:17.503Z",
        "updatedAt": "2025-04-14T18:47:17.503Z",
        "publishedAt": "2025-04-14T18:47:17.504Z"
      },
      {
        "id": 18,
        "documentId": "f88mnhhmgftxmi3euw2j6i13",
        "name": "Living Room-3.jpg",
        "alternativeText": null,
        "caption": null,
        "width": 1600,
        "height": 900,
        "formats": {
          "thumbnail": {
            "name": "thumbnail_Living Room-3.jpg",
            "hash": "thumbnail_Living_Room_3_9a9ffb5765",
            "ext": ".jpg",
            "mime": "image/jpeg",
            "path": null,
            "width": 245,
            "height": 138,
            "size": 9.57,
            "sizeInBytes": 9570,
            "url": "/uploads/thumbnail_Living_Room_3_9a9ffb5765.jpg"
          },
          "small": {
            "name": "small_Living Room-3.jpg",
            "hash": "small_Living_Room_3_9a9ffb5765",
            "ext": ".jpg",
            "mime": "image/jpeg",
            "path": null,
            "width": 500,
            "height": 281,
            "size": 29.72,
            "sizeInBytes": 29724,
            "url": "/uploads/small_Living_Room_3_9a9ffb5765.jpg"
          },
          "medium": {
            "name": "medium_Living Room-3.jpg",
            "hash": "medium_Living_Room_3_9a9ffb5765",
            "ext": ".jpg",
            "mime": "image/jpeg",
            "path": null,
            "width": 750,
            "height": 422,
            "size": 57.92,
            "sizeInBytes": 57916,
            "url": "/uploads/medium_Living_Room_3_9a9ffb5765.jpg"
          },
          "large": {
            "name": "large_Living Room-3.jpg",
            "hash": "large_Living_Room_3_9a9ffb5765",
            "ext": ".jpg",
            "mime": "image/jpeg",
            "path": null,
            "width": 1000,
            "height": 563,
            "size": 92.11,
            "sizeInBytes": 92110,
            "url": "/uploads/large_Living_Room_3_9a9ffb5765.jpg"
          }
        },
        "hash": "Living_Room_3_9a9ffb5765",
        "ext": ".jpg",
        "mime": "image/jpeg",
        "size": 167.48,
        "url": "/uploads/Living_Room_3_9a9ffb5765.jpg",
        "previewUrl": null,
        "provider": "local",
        "provider_metadata": null,
        "createdAt": "2025-04-14T18:47:17.792Z",
        "updatedAt": "2025-04-14T18:47:17.792Z",
        "publishedAt": "2025-04-14T18:47:17.792Z"
      },
      {
        "id": 19,
        "documentId": "jatwjqhcdh3r0705hekwyhhq",
        "name": "Living Room-2.jpg",
        "alternativeText": null,
        "caption": null,
        "width": 900,
        "height": 1600,
        "formats": {
          "thumbnail": {
            "name": "thumbnail_Living Room-2.jpg",
            "hash": "thumbnail_Living_Room_2_d8f9026559",
            "ext": ".jpg",
            "mime": "image/jpeg",
            "path": null,
            "width": 87,
            "height": 156,
            "size": 3.47,
            "sizeInBytes": 3472,
            "url": "/uploads/thumbnail_Living_Room_2_d8f9026559.jpg"
          },
          "medium": {
            "name": "medium_Living Room-2.jpg",
            "hash": "medium_Living_Room_2_d8f9026559",
            "ext": ".jpg",
            "mime": "image/jpeg",
            "path": null,
            "width": 422,
            "height": 750,
            "size": 44.63,
            "sizeInBytes": 44626,
            "url": "/uploads/medium_Living_Room_2_d8f9026559.jpg"
          },
          "small": {
            "name": "small_Living Room-2.jpg",
            "hash": "small_Living_Room_2_d8f9026559",
            "ext": ".jpg",
            "mime": "image/jpeg",
            "path": null,
            "width": 281,
            "height": 500,
            "size": 22.71,
            "sizeInBytes": 22708,
            "url": "/uploads/small_Living_Room_2_d8f9026559.jpg"
          },
          "large": {
            "name": "large_Living Room-2.jpg",
            "hash": "large_Living_Room_2_d8f9026559",
            "ext": ".jpg",
            "mime": "image/jpeg",
            "path": null,
            "width": 563,
            "height": 1000,
            "size": 71.51,
            "sizeInBytes": 71506,
            "url": "/uploads/large_Living_Room_2_d8f9026559.jpg"
          }
        },
        "hash": "Living_Room_2_d8f9026559",
        "ext": ".jpg",
        "mime": "image/jpeg",
        "size": 129.63,
        "url": "/uploads/Living_Room_2_d8f9026559.jpg",
        "previewUrl": null,
        "provider": "local",
        "provider_metadata": null,
        "createdAt": "2025-04-14T18:47:17.795Z",
        "updatedAt": "2025-04-14T18:47:17.795Z",
        "publishedAt": "2025-04-14T18:47:17.795Z"
      },
      {
        "id": 20,
        "documentId": "eipkat3qgztfd3f9y3nxbb1b",
        "name": "Living Room-1.jpg",
        "alternativeText": null,
        "caption": null,
        "width": 900,
        "height": 1600,
        "formats": {
          "thumbnail": {
            "name": "thumbnail_Living Room-1.jpg",
            "hash": "thumbnail_Living_Room_1_eb6a5d5fcb",
            "ext": ".jpg",
            "mime": "image/jpeg",
            "path": null,
            "width": 87,
            "height": 156,
            "size": 3.74,
            "sizeInBytes": 3742,
            "url": "/uploads/thumbnail_Living_Room_1_eb6a5d5fcb.jpg"
          },
          "medium": {
            "name": "medium_Living Room-1.jpg",
            "hash": "medium_Living_Room_1_eb6a5d5fcb",
            "ext": ".jpg",
            "mime": "image/jpeg",
            "path": null,
            "width": 422,
            "height": 750,
            "size": 47.72,
            "sizeInBytes": 47718,
            "url": "/uploads/medium_Living_Room_1_eb6a5d5fcb.jpg"
          },
          "small": {
            "name": "small_Living Room-1.jpg",
            "hash": "small_Living_Room_1_eb6a5d5fcb",
            "ext": ".jpg",
            "mime": "image/jpeg",
            "path": null,
            "width": 281,
            "height": 500,
            "size": 23.85,
            "sizeInBytes": 23845,
            "url": "/uploads/small_Living_Room_1_eb6a5d5fcb.jpg"
          },
          "large": {
            "name": "large_Living Room-1.jpg",
            "hash": "large_Living_Room_1_eb6a5d5fcb",
            "ext": ".jpg",
            "mime": "image/jpeg",
            "path": null,
            "width": 563,
            "height": 1000,
            "size": 78.73,
            "sizeInBytes": 78734,
            "url": "/uploads/large_Living_Room_1_eb6a5d5fcb.jpg"
          }
        },
        "hash": "Living_Room_1_eb6a5d5fcb",
        "ext": ".jpg",
        "mime": "image/jpeg",
        "size": 146.01,
        "url": "/uploads/Living_Room_1_eb6a5d5fcb.jpg",
        "previewUrl": null,
        "provider": "local",
        "provider_metadata": null,
        "createdAt": "2025-04-14T18:47:17.797Z",
        "updatedAt": "2025-04-14T18:47:17.797Z",
        "publishedAt": "2025-04-14T18:47:17.797Z"
      },
      {
        "id": 21,
        "documentId": "wunmqnodyzmhqsmubwokktpr",
        "name": "Living Room-4.jpg",
        "alternativeText": null,
        "caption": null,
        "width": 900,
        "height": 1600,
        "formats": {
          "thumbnail": {
            "name": "thumbnail_Living Room-4.jpg",
            "hash": "thumbnail_Living_Room_4_716e5d5c7c",
            "ext": ".jpg",
            "mime": "image/jpeg",
            "path": null,
            "width": 87,
            "height": 156,
            "size": 4.17,
            "sizeInBytes": 4173,
            "url": "/uploads/thumbnail_Living_Room_4_716e5d5c7c.jpg"
          },
          "medium": {
            "name": "medium_Living Room-4.jpg",
            "hash": "medium_Living_Room_4_716e5d5c7c",
            "ext": ".jpg",
            "mime": "image/jpeg",
            "path": null,
            "width": 422,
            "height": 750,
            "size": 55.34,
            "sizeInBytes": 55335,
            "url": "/uploads/medium_Living_Room_4_716e5d5c7c.jpg"
          },
          "small": {
            "name": "small_Living Room-4.jpg",
            "hash": "small_Living_Room_4_716e5d5c7c",
            "ext": ".jpg",
            "mime": "image/jpeg",
            "path": null,
            "width": 281,
            "height": 500,
            "size": 28.31,
            "sizeInBytes": 28306,
            "url": "/uploads/small_Living_Room_4_716e5d5c7c.jpg"
          },
          "large": {
            "name": "large_Living Room-4.jpg",
            "hash": "large_Living_Room_4_716e5d5c7c",
            "ext": ".jpg",
            "mime": "image/jpeg",
            "path": null,
            "width": 563,
            "height": 1000,
            "size": 87.42,
            "sizeInBytes": 87423,
            "url": "/uploads/large_Living_Room_4_716e5d5c7c.jpg"
          }
        },
        "hash": "Living_Room_4_716e5d5c7c",
        "ext": ".jpg",
        "mime": "image/jpeg",
        "size": 154.49,
        "url": "/uploads/Living_Room_4_716e5d5c7c.jpg",
        "previewUrl": null,
        "provider": "local",
        "provider_metadata": null,
        "createdAt": "2025-04-14T18:47:17.854Z",
        "updatedAt": "2025-04-14T18:47:17.854Z",
        "publishedAt": "2025-04-14T18:47:17.855Z"
      },
      {
        "id": 22,
        "documentId": "hy6pwxdi6kyv0xq2abevt6ep",
        "name": "Living Room-5.jpg",
        "alternativeText": null,
        "caption": null,
        "width": 1600,
        "height": 900,
        "formats": {
          "thumbnail": {
            "name": "thumbnail_Living Room-5.jpg",
            "hash": "thumbnail_Living_Room_5_f593c1861b",
            "ext": ".jpg",
            "mime": "image/jpeg",
            "path": null,
            "width": 245,
            "height": 138,
            "size": 9.58,
            "sizeInBytes": 9576,
            "url": "/uploads/thumbnail_Living_Room_5_f593c1861b.jpg"
          },
          "medium": {
            "name": "medium_Living Room-5.jpg",
            "hash": "medium_Living_Room_5_f593c1861b",
            "ext": ".jpg",
            "mime": "image/jpeg",
            "path": null,
            "width": 750,
            "height": 422,
            "size": 59.66,
            "sizeInBytes": 59657,
            "url": "/uploads/medium_Living_Room_5_f593c1861b.jpg"
          },
          "small": {
            "name": "small_Living Room-5.jpg",
            "hash": "small_Living_Room_5_f593c1861b",
            "ext": ".jpg",
            "mime": "image/jpeg",
            "path": null,
            "width": 500,
            "height": 281,
            "size": 30.51,
            "sizeInBytes": 30512,
            "url": "/uploads/small_Living_Room_5_f593c1861b.jpg"
          },
          "large": {
            "name": "large_Living Room-5.jpg",
            "hash": "large_Living_Room_5_f593c1861b",
            "ext": ".jpg",
            "mime": "image/jpeg",
            "path": null,
            "width": 1000,
            "height": 563,
            "size": 95.34,
            "sizeInBytes": 95336,
            "url": "/uploads/large_Living_Room_5_f593c1861b.jpg"
          }
        },
        "hash": "Living_Room_5_f593c1861b",
        "ext": ".jpg",
        "mime": "image/jpeg",
        "size": 169.03,
        "url": "/uploads/Living_Room_5_f593c1861b.jpg",
        "previewUrl": null,
        "provider": "local",
        "provider_metadata": null,
        "createdAt": "2025-04-14T18:47:17.891Z",
        "updatedAt": "2025-04-14T18:47:17.891Z",
        "publishedAt": "2025-04-14T18:47:17.891Z"
      },
      {
        "id": 23,
        "documentId": "ua9bxiue0qlfgpcdwy1c20l3",
        "name": "Others-1.jpg",
        "alternativeText": null,
        "caption": null,
        "width": 900,
        "height": 1600,
        "formats": {
          "thumbnail": {
            "name": "thumbnail_Others-1.jpg",
            "hash": "thumbnail_Others_1_d6c8d20686",
            "ext": ".jpg",
            "mime": "image/jpeg",
            "path": null,
            "width": 87,
            "height": 156,
            "size": 3.36,
            "sizeInBytes": 3361,
            "url": "/uploads/thumbnail_Others_1_d6c8d20686.jpg"
          },
          "medium": {
            "name": "medium_Others-1.jpg",
            "hash": "medium_Others_1_d6c8d20686",
            "ext": ".jpg",
            "mime": "image/jpeg",
            "path": null,
            "width": 422,
            "height": 750,
            "size": 50.97,
            "sizeInBytes": 50974,
            "url": "/uploads/medium_Others_1_d6c8d20686.jpg"
          },
          "small": {
            "name": "small_Others-1.jpg",
            "hash": "small_Others_1_d6c8d20686",
            "ext": ".jpg",
            "mime": "image/jpeg",
            "path": null,
            "width": 281,
            "height": 500,
            "size": 24.93,
            "sizeInBytes": 24925,
            "url": "/uploads/small_Others_1_d6c8d20686.jpg"
          },
          "large": {
            "name": "large_Others-1.jpg",
            "hash": "large_Others_1_d6c8d20686",
            "ext": ".jpg",
            "mime": "image/jpeg",
            "path": null,
            "width": 563,
            "height": 1000,
            "size": 82.37,
            "sizeInBytes": 82371,
            "url": "/uploads/large_Others_1_d6c8d20686.jpg"
          }
        },
        "hash": "Others_1_d6c8d20686",
        "ext": ".jpg",
        "mime": "image/jpeg",
        "size": 152.88,
        "url": "/uploads/Others_1_d6c8d20686.jpg",
        "previewUrl": null,
        "provider": "local",
        "provider_metadata": null,
        "createdAt": "2025-04-14T18:47:17.907Z",
        "updatedAt": "2025-04-14T18:47:17.907Z",
        "publishedAt": "2025-04-14T18:47:17.908Z"
      },
      {
        "id": 24,
        "documentId": "oknzf1t03sm8f0ep1z4uetb0",
        "name": "Pool-1.jpg",
        "alternativeText": null,
        "caption": null,
        "width": 900,
        "height": 1600,
        "formats": {
          "thumbnail": {
            "name": "thumbnail_Pool-1.jpg",
            "hash": "thumbnail_Pool_1_24a92f3c8b",
            "ext": ".jpg",
            "mime": "image/jpeg",
            "path": null,
            "width": 87,
            "height": 156,
            "size": 4.72,
            "sizeInBytes": 4725,
            "url": "/uploads/thumbnail_Pool_1_24a92f3c8b.jpg"
          },
          "small": {
            "name": "small_Pool-1.jpg",
            "hash": "small_Pool_1_24a92f3c8b",
            "ext": ".jpg",
            "mime": "image/jpeg",
            "path": null,
            "width": 281,
            "height": 500,
            "size": 36.46,
            "sizeInBytes": 36459,
            "url": "/uploads/small_Pool_1_24a92f3c8b.jpg"
          },
          "large": {
            "name": "large_Pool-1.jpg",
            "hash": "large_Pool_1_24a92f3c8b",
            "ext": ".jpg",
            "mime": "image/jpeg",
            "path": null,
            "width": 563,
            "height": 1000,
            "size": 121.46,
            "sizeInBytes": 121456,
            "url": "/uploads/large_Pool_1_24a92f3c8b.jpg"
          },
          "medium": {
            "name": "medium_Pool-1.jpg",
            "hash": "medium_Pool_1_24a92f3c8b",
            "ext": ".jpg",
            "mime": "image/jpeg",
            "path": null,
            "width": 422,
            "height": 750,
            "size": 74.6,
            "sizeInBytes": 74600,
            "url": "/uploads/medium_Pool_1_24a92f3c8b.jpg"
          }
        },
        "hash": "Pool_1_24a92f3c8b",
        "ext": ".jpg",
        "mime": "image/jpeg",
        "size": 224.75,
        "url": "/uploads/Pool_1_24a92f3c8b.jpg",
        "previewUrl": null,
        "provider": "local",
        "provider_metadata": null,
        "createdAt": "2025-04-14T18:47:17.975Z",
        "updatedAt": "2025-04-14T18:47:17.975Z",
        "publishedAt": "2025-04-14T18:47:17.975Z"
      },
      {
        "id": 25,
        "documentId": "ed43i8s4nrxyo95veilxzw23",
        "name": "Pool-2.jpg",
        "alternativeText": null,
        "caption": null,
        "width": 900,
        "height": 1600,
        "formats": {
          "thumbnail": {
            "name": "thumbnail_Pool-2.jpg",
            "hash": "thumbnail_Pool_2_3aed89594f",
            "ext": ".jpg",
            "mime": "image/jpeg",
            "path": null,
            "width": 87,
            "height": 156,
            "size": 4.87,
            "sizeInBytes": 4869,
            "url": "/uploads/thumbnail_Pool_2_3aed89594f.jpg"
          },
          "small": {
            "name": "small_Pool-2.jpg",
            "hash": "small_Pool_2_3aed89594f",
            "ext": ".jpg",
            "mime": "image/jpeg",
            "path": null,
            "width": 281,
            "height": 500,
            "size": 45.61,
            "sizeInBytes": 45605,
            "url": "/uploads/small_Pool_2_3aed89594f.jpg"
          },
          "large": {
            "name": "large_Pool-2.jpg",
            "hash": "large_Pool_2_3aed89594f",
            "ext": ".jpg",
            "mime": "image/jpeg",
            "path": null,
            "width": 563,
            "height": 1000,
            "size": 158.82,
            "sizeInBytes": 158816,
            "url": "/uploads/large_Pool_2_3aed89594f.jpg"
          },
          "medium": {
            "name": "medium_Pool-2.jpg",
            "hash": "medium_Pool_2_3aed89594f",
            "ext": ".jpg",
            "mime": "image/jpeg",
            "path": null,
            "width": 422,
            "height": 750,
            "size": 96.41,
            "sizeInBytes": 96414,
            "url": "/uploads/medium_Pool_2_3aed89594f.jpg"
          }
        },
        "hash": "Pool_2_3aed89594f",
        "ext": ".jpg",
        "mime": "image/jpeg",
        "size": 306.44,
        "url": "/uploads/Pool_2_3aed89594f.jpg",
        "previewUrl": null,
        "provider": "local",
        "provider_metadata": null,
        "createdAt": "2025-04-14T18:47:17.983Z",
        "updatedAt": "2025-04-14T18:47:17.983Z",
        "publishedAt": "2025-04-14T18:47:17.984Z"
      }
    ],
    "MainImage": {
      "id": 14,
      "documentId": "xjeuuo072kwwo2czppdj0qwp",
      "name": "Exterior-1.jpg",
      "alternativeText": null,
      "caption": null,
      "width": 900,
      "height": 1600,
      "formats": {
        "thumbnail": {
          "name": "thumbnail_Exterior-1.jpg",
          "hash": "thumbnail_Exterior_1_5968f3b2b7",
          "ext": ".jpg",
          "mime": "image/jpeg",
          "path": null,
          "width": 87,
          "height": 156,
          "size": 4.47,
          "sizeInBytes": 4467,
          "url": "/uploads/thumbnail_Exterior_1_5968f3b2b7.jpg"
        },
        "small": {
          "name": "small_Exterior-1.jpg",
          "hash": "small_Exterior_1_5968f3b2b7",
          "ext": ".jpg",
          "mime": "image/jpeg",
          "path": null,
          "width": 281,
          "height": 500,
          "size": 34.24,
          "sizeInBytes": 34241,
          "url": "/uploads/small_Exterior_1_5968f3b2b7.jpg"
        },
        "large": {
          "name": "large_Exterior-1.jpg",
          "hash": "large_Exterior_1_5968f3b2b7",
          "ext": ".jpg",
          "mime": "image/jpeg",
          "path": null,
          "width": 563,
          "height": 1000,
          "size": 114.93,
          "sizeInBytes": 114928,
          "url": "/uploads/large_Exterior_1_5968f3b2b7.jpg"
        },
        "medium": {
          "name": "medium_Exterior-1.jpg",
          "hash": "medium_Exterior_1_5968f3b2b7",
          "ext": ".jpg",
          "mime": "image/jpeg",
          "path": null,
          "width": 422,
          "height": 750,
          "size": 70.18,
          "sizeInBytes": 70183,
          "url": "/uploads/medium_Exterior_1_5968f3b2b7.jpg"
        }
      },
      "hash": "Exterior_1_5968f3b2b7",
      "ext": ".jpg",
      "mime": "image/jpeg",
      "size": 221.94,
      "url": "/uploads/Exterior_1_5968f3b2b7.jpg",
      "previewUrl": null,
      "provider": "local",
      "provider_metadata": null,
      "createdAt": "2025-04-14T18:47:17.482Z",
      "updatedAt": "2025-04-14T20:18:36.870Z",
      "publishedAt": "2025-04-14T18:47:17.482Z"
    },
    "propertyLocation": {
      "id": 7,
      "address": "Jl. Situbanda, MAS, Kecamatan Ubud, Kabupaten Gianyar, Bali 80571",
      "latitude": null,
      "longitude": null,
      "mapUrl": null
    },
    "Amenities": [
      {
        "id": 34,
        "amenityName": "Swimming Pool"
      },
      {
        "id": 35,
        "amenityName": "Parking"
      },
      {
        "id": 36,
        "amenityName": "Air Conditioning"
      },
      {
        "id": 37,
        "amenityName": "WiFi"
      },
      {
        "id": 38,
        "amenityName": "Kitchen"
      },
      {
        "id": 39,
        "amenityName": "TV"
      },
      {
        "id": 40,
        "amenityName": "Balcony"
      },
      {
        "id": 41,
        "amenityName": "Rice Field View"
      },
      {
        "id": 42,
        "amenityName": "Living Room"
      }
    ]
  }
]